kruncherclient/__init__.py
kruncherclient/client.py
kruncherclient/exceptions.py
kruncherclient-0.1.1.dist-info/LICENSE
kruncherclient-0.1.1.dist-info/METADATA
kruncherclient-0.1.1.dist-info/WHEEL
kruncherclient-0.1.1.dist-info/top_level.txt
kruncherclient-0.1.1.dist-info/RECORD
