Metadata-Version: 2.2
Name: kruncherclient
Version: 0.1.1
Summary: A Python client for the Kruncher API
Author-email: Andrea Dorigo <andrea@kruncher.ai>
License:                                  Apache License
Project-URL: Homepage, https://github.com/kruncherai/kruncher-client
Classifier: Programming Language :: Python :: 3
Classifier: License :: OSI Approved :: MIT License
Classifier: Operating System :: OS Independent
Requires-Python: >=3.09
License-File: LICENSE
Requires-Dist: requests>=2.25.0
Requires-Dist: pandas>=1.2.0
Requires-Dist: python-dotenv>=0.19.0
